{
	"info": {
		"_postman_id": "dc84670b-94b2-432f-8611-aa0d8709b1a6",
		"name": "Cat Facts Copy",
		"description": "Contact Support:\n Name: Amanda Nickels\n Email: admin@admin.com",
		"schema": "https://schema.getpostman.com/json/collection/v2.0.0/collection.json"
	},
	"item": [
		{
			"name": "Returns a list of breeds",
			"_postman_id": "66397189-c6f5-44af-bc51-b03d07c9c34c",
			"protocolProfileBehavior": {
				"disableBodyPruning": true
			},
			"request": {
				"method": "GET",
				"header": [
					{
						"key": "Accept",
						"value": "application/json"
					}
				],
				"url": {
					"raw": "{{baseUrl}}/breeds?limit=10",
					"host": [
						"{{baseUrl}}"
					],
					"path": [
						"breeds"
					],
					"query": [
						{
							"description": "limit list size",
							"key": "limit",
							"value": "10"
						}
					]
				},
				"description": "Returns a list of breeds"
			},
			"response": [
				{
					"id": "09959b69-38d9-46d2-be6a-3fed7d04d8d7",
					"name": "Normal operation",
					"originalRequest": {
						"method": "GET",
						"header": [
							{
								"key": "Accept",
								"value": "application/json"
							},
							{
								"description": "Added as a part of security scheme: basic",
								"key": "Authorization",
								"value": "Basic <credentials>"
							}
						],
						"url": {
							"raw": "{{baseUrl}}/breeds?limit=10",
							"host": [
								"{{baseUrl}}"
							],
							"path": [
								"breeds"
							],
							"query": [
								{
									"description": "limit list size",
									"key": "limit",
									"value": "10"
								}
							]
						}
					},
					"status": "OK",
					"code": 200,
					"_postman_previewlanguage": "json",
					"header": [
						{
							"key": "Content-Type",
							"value": "application/json"
						}
					],
					"cookie": [],
					"responseTime": null,
					"body": "[\n  {\n    \"breed\": \"ad in Ut\",\n    \"country\": \"dolore Excepteur velit ea\",\n    \"origin\": \"laborum\",\n    \"coat\": \"Lorem sed minim consequat\",\n    \"pattern\": \"elit ven\"\n  },\n  {\n    \"breed\": \"officia \",\n    \"country\": \"Duis\",\n    \"origin\": \"elit dolore ex eiusmod et\",\n    \"coat\": \"aute\",\n    \"pattern\": \"laborum id et\"\n  }\n]"
				},
				{
					"id": "d7137e6d-80bd-4835-b69d-57150e3a7983",
					"name": "Server exception",
					"originalRequest": {
						"method": "GET",
						"header": [
							{
								"key": "Accept",
								"value": "application/json"
							},
							{
								"description": "Added as a part of security scheme: basic",
								"key": "Authorization",
								"value": "Basic <credentials>"
							}
						],
						"url": {
							"raw": "{{baseUrl}}/breeds?limit=10",
							"host": [
								"{{baseUrl}}"
							],
							"path": [
								"breeds"
							],
							"query": [
								{
									"description": "limit list size",
									"key": "limit",
									"value": "10"
								}
							]
						}
					},
					"status": "Internal Server Error",
					"code": 500,
					"_postman_previewlanguage": "json",
					"header": [
						{
							"key": "Content-Type",
							"value": "application/json"
						}
					],
					"cookie": [],
					"responseTime": null,
					"body": "internal server error"
				}
			]
		},
		{
			"name": "Returns a random fact",
			"_postman_id": "735b968a-9f75-4392-997e-956d999a3451",
			"protocolProfileBehavior": {
				"disableBodyPruning": true
			},
			"request": {
				"method": "GET",
				"header": [
					{
						"key": "Accept",
						"value": "application/json"
					}
				],
				"url": {
					"raw": "{{baseUrl}}/fact?max_length=30",
					"host": [
						"{{baseUrl}}"
					],
					"path": [
						"fact"
					],
					"query": [
						{
							"key": "max_length",
							"value": "30",
							"description": "maximum length of returned fact"
						}
					]
				},
				"description": "Returns a random fact"
			},
			"response": [
				{
					"id": "60b0241c-d23e-46fc-80e3-8fe4d8970a2b",
					"name": "Normal operation",
					"originalRequest": {
						"method": "GET",
						"header": [
							{
								"key": "Accept",
								"value": "application/json"
							},
							{
								"description": "Added as a part of security scheme: basic",
								"key": "Authorization",
								"value": "Basic <credentials>"
							}
						],
						"url": {
							"raw": "{{baseUrl}}/fact?max_length=30",
							"host": [
								"{{baseUrl}}"
							],
							"path": [
								"fact"
							],
							"query": [
								{
									"description": "maximum length of returned fact",
									"key": "max_length",
									"value": "30"
								}
							]
						}
					},
					"status": "OK",
					"code": 200,
					"_postman_previewlanguage": "json",
					"header": [
						{
							"key": "Content-Type",
							"value": "application/json"
						}
					],
					"cookie": [],
					"responseTime": null,
					"body": "{\n  \"fact\": \"This is an excample fact about cats!\",\n  \"length\": 33\n}"
				},
				{
					"id": "d7f645ec-c404-4155-a4f8-cd3174ffa58b",
					"name": "Server exception",
					"originalRequest": {
						"method": "GET",
						"header": [
							{
								"key": "Accept",
								"value": "application/json"
							},
							{
								"description": "Added as a part of security scheme: basic",
								"key": "Authorization",
								"value": "Basic <credentials>"
							}
						],
						"url": {
							"raw": "{{baseUrl}}/fact?max_length=30",
							"host": [
								"{{baseUrl}}"
							],
							"path": [
								"fact"
							],
							"query": [
								{
									"description": "maximum length of returned fact",
									"key": "max_length",
									"value": "30"
								}
							]
						}
					},
					"status": "Internal Server Error",
					"code": 500,
					"_postman_previewlanguage": "json",
					"header": [
						{
							"key": "Content-Type",
							"value": "application/json"
						}
					],
					"cookie": [],
					"responseTime": null,
					"body": "internal server error"
				}
			]
		},
		{
			"name": "Get a list of facts",
			"_postman_id": "5a681fe5-1058-46f5-a9ba-c254e4a80e81",
			"protocolProfileBehavior": {
				"disableBodyPruning": true
			},
			"request": {
				"method": "GET",
				"header": [
					{
						"key": "Accept",
						"value": "application/json"
					}
				],
				"url": {
					"raw": "{{baseUrl}}/facts?max_length=30&limit=10",
					"host": [
						"{{baseUrl}}"
					],
					"path": [
						"facts"
					],
					"query": [
						{
							"description": "length",
							"key": "max_length",
							"value": "30"
						},
						{
							"description": "limit the amount of results returned",
							"key": "limit",
							"value": "10"
						}
					]
				},
				"description": "Returns a a list of facts"
			},
			"response": [
				{
					"id": "14d77a1e-2a9b-4952-8f88-29df151d0867",
					"name": "Server exception",
					"originalRequest": {
						"method": "GET",
						"header": [
							{
								"key": "Accept",
								"value": "application/json"
							},
							{
								"description": "Added as a part of security scheme: basic",
								"key": "Authorization",
								"value": "Basic <credentials>"
							}
						],
						"url": {
							"raw": "{{baseUrl}}/facts?max_length=30&limit=10",
							"host": [
								"{{baseUrl}}"
							],
							"path": [
								"facts"
							],
							"query": [
								{
									"description": "length",
									"key": "max_length",
									"value": "30"
								},
								{
									"description": "limit the amount of results returned",
									"key": "limit",
									"value": "10"
								}
							]
						}
					},
					"status": "Internal Server Error",
					"code": 500,
					"_postman_previewlanguage": "json",
					"header": [
						{
							"key": "Content-Type",
							"value": "application/json"
						}
					],
					"cookie": [],
					"responseTime": null,
					"body": "internal server error"
				},
				{
					"id": "3ff55b43-a6f3-43aa-b404-0821f5731721",
					"name": "Normal operation",
					"originalRequest": {
						"method": "GET",
						"header": [
							{
								"key": "Accept",
								"value": "application/json"
							},
							{
								"description": "Added as a part of security scheme: basic",
								"key": "Authorization",
								"value": "Basic <credentials>"
							}
						],
						"url": {
							"raw": "{{baseUrl}}/facts?max_length=30&limit=10",
							"host": [
								"{{baseUrl}}"
							],
							"path": [
								"facts"
							],
							"query": [
								{
									"description": "length",
									"key": "max_length",
									"value": "30"
								},
								{
									"description": "limit the amount of results returned",
									"key": "limit",
									"value": "10"
								}
							]
						}
					},
					"status": "OK",
					"code": 200,
					"_postman_previewlanguage": "json",
					"header": [
						{
							"key": "Content-Type",
							"value": "application/json"
						}
					],
					"cookie": [],
					"responseTime": null,
					"body": "[\n  {\n    \"fact\": \"This is an excample fact about cats!\",\n    \"length\": 33\n  },\n  {\n    \"fact\": \"This is an excample fact about cats!\",\n    \"length\": 33\n  }\n]"
				}
			]
		}
	],
	"auth": {
		"type": "basic",
		"basic": {
			"username": "{{basicAuthUsername}}",
			"password": "{{basicAuthPassword}}"
		}
	},
	"variable": [
		{
			"id": "23c3f183-a474-4b33-9e25-59264b2f9c77",
			"key": "baseUrl",
			"value": "https://catfact.ninja",
			"type": "string"
		}
	]
}